count_unique_chars/__init__.py
count_unique_chars/cli.py
count_unique_chars/count_unique_chars.py
count_unique_chars/exceptions.py
count_unique_chars-0.0.4.dist-info/METADATA
count_unique_chars-0.0.4.dist-info/WHEEL
count_unique_chars-0.0.4.dist-info/entry_points.txt
count_unique_chars-0.0.4.dist-info/licenses/LICENSE
count_unique_chars-0.0.4.dist-info/RECORD
