Metadata-Version: 2.1
Name: count-unique-chars
Version: 0.0.4
Summary: A utility to count the number of unique characters in a string or file.
Author-email: Ilya Mishakin <imishakintyr@gmail.com>
License-File: LICENSE
Classifier: License :: OSI Approved :: MIT License
Classifier: Operating System :: OS Independent
Classifier: Programming Language :: Python :: 3
Requires-Python: >=3.7
